{
  "widgetId": "pnl-by-client",
  "label": "P&L by Client",
  "priority": 3,
  "domain": "pnl",
  "file": "components/widgets/pnl/pnl-by-client-widget.tsx",
  "class": "inline-table",
  "description": "Client-level P&L table with org, active strategy count, daily change, and percentage change.",
  "levels": {
    "l0": {
      "status": null,
      "by": null,
      "date": null,
      "notes": null
    },
    "l1": {
      "status": null,
      "by": null,
      "date": null,
      "notes": null
    },
    "l2": {
      "status": null,
      "by": null,
      "date": null,
      "notes": null
    },
    "l3": {
      "status": null,
      "by": null,
      "date": null,
      "notes": null
    },
    "l4": {
      "status": null,
      "by": null,
      "date": null,
      "notes": null
    },
    "l5": {
      "status": null,
      "by": null,
      "date": null,
      "notes": null
    },
    "l6": {
      "status": null,
      "by": null,
      "date": null,
      "notes": null
    }
  },
  "knownIssues": [],
  "findings": [],
  "updatedBy": null,
  "updatedAt": null
}
