{
  "widgetId": "pred-trade-panel",
  "label": "Quick Trade",
  "priority": 5,
  "domain": "predictions",
  "file": "components/widgets/predictions/pred-trade-panel-widget.tsx",
  "class": "bespoke",
  "description": "Market selector and trade panel with Kelly stake suggestion for prediction markets.",
  "levels": {
    "l0": {
      "status": "pass",
      "by": "agent",
      "date": "2026-04-17",
      "checks": {
        "0.1": {
          "result": "pass",
          "note": "WidgetErrorBoundary via widget-wrapper.tsx."
        },
        "0.2": {
          "result": "pass",
          "note": "requiredEntitlements: [{domain:'trading-predictions',tier:'basic'}]."
        },
        "0.3": {
          "result": "pass",
          "note": "availableOn: ['predictions']."
        },
        "0.4": {
          "result": "pass",
          "note": "No any or @ts-ignore."
        },
        "0.5": {
          "result": "pass",
          "note": "No lib/mocks/ imports in widget file."
        },
        "0.6": {
          "result": "pass",
          "note": "Sync context; no loading state needed."
        },
        "0.7": {
          "result": "pass",
          "note": "Empty state: Search icon + 'Search or select a market above' when no market selected."
        },
        "0.8": {
          "result": "pass",
          "note": "WidgetErrorBoundary covers provider throw."
        },
        "0.9": {
          "result": "pass",
          "note": "No dead code."
        }
      },
      "notes": "All 9 checks pass."
    },
    "l1": {
      "status": "pass",
      "by": "agent",
      "date": "2026-04-17",
      "checks": {
        "1.1": {
          "result": "pass",
          "note": "Reads markets, quickTradeMarketId, setQuickTradeMarketId, placeTrade via usePredictionsData()."
        },
        "1.2": {
          "result": "pass",
          "note": "Context calls useGlobalScope()."
        },
        "1.3": {
          "result": "pass",
          "note": "Market list is global catalogue \u2014 not org-scoped."
        },
        "1.4": {
          "result": "pass",
          "note": "clientIds gap acknowledged."
        },
        "1.5": {
          "result": "pass",
          "note": "Strategy filter N/A for trade panel market selector."
        },
        "1.6": {
          "result": "pass",
          "note": "Empty scope shows all markets."
        },
        "1.7": {
          "result": "pass",
          "note": "No lib/mocks/ in widget file."
        }
      },
      "notes": "All L1 pass."
    },
    "l2": {
      "status": "pass",
      "by": "agent+tests",
      "date": "2026-04-21",
      "notes": "Covered globally by commits 32ba8ab + f9f29ea."
    },
    "l3": {
      "status": "partial",
      "by": "agent",
      "date": "2026-04-21",
      "checks": {
        "3.1": {
          "result": "pass",
          "note": "Live \u2713: real trade placement. Paper \u2713: placeTrade posts simulated. Batch \u2713: trade submission should be disabled."
        },
        "3.2": {
          "result": "pass",
          "note": "Context reads isBatch; placeTrade calls placeMockOrder (batch-safe) but ideally disabled."
        },
        "3.5": {
          "result": "pass",
          "note": "Paper: placeTrade produces simulated fill entry. Human verify toast shows simulated context."
        },
        "3.6": {
          "result": "pass",
          "note": "No interval in this widget."
        }
      },
      "notes": "Agent prep complete. Human: 3.3 \u2014 verify trade button disabled in batch mode; 3.4 \u2014 batch indicator visible."
    },
    "l4": {
      "status": "partial",
      "by": "agent",
      "date": "2026-04-21",
      "checks": {
        "4.1": {
          "result": "pass",
          "note": "MarketSelector and TradePanelInner delegate interactions \u2014 setQuickTradeMarketId and placeTrade both wired."
        },
        "4.2": {
          "result": "pass",
          "note": "No dead links."
        },
        "4.5": {
          "result": "pass",
          "note": "No gated routes."
        },
        "4.6": {
          "result": "pass",
          "note": "No per-render entitlement checks."
        }
      },
      "notes": "Human: 4.3/4.4 \u2014 form fields (market, outcome, side, stake, Kelly suggestion) present and submit produces fill; 4.7 N/A; 4.8 scroll."
    },
    "l5": {
      "status": "partial",
      "by": "agent",
      "date": "2026-04-21",
      "checks": {
        "5.1": {
          "result": "pass",
          "note": "Primary trade entry for PRED_POLY_ARB_SCE_1M, PREDICTION_POLY_ML_DIR_EVT_4H, PRED_BTC_CEFI_ARB_SCE_5M. Widget includes Kelly sizing suggestion."
        }
      },
      "notes": "Agent prep complete. Human: full trade flow \u2014 select market \u2192 choose outcome \u2192 enter stake \u2192 place \u2192 verify fill in recent fills + open positions."
    },
    "l6": {
      "status": null,
      "by": null,
      "date": null,
      "notes": null
    },
    "l7": {
      "status": "pass",
      "by": "agent",
      "date": "2026-04-21",
      "checks": {
        "7.1": {
          "result": "pass",
          "note": "No hardcoded hex/rgb in widget file."
        },
        "7.2": {
          "result": "pass",
          "note": "No lib/mocks/ imports."
        },
        "7.3": {
          "result": "pass",
          "note": "25 lines \u2014 minimal, delegates to MarketSelector and TradePanelInner."
        },
        "7.4": {
          "result": "pass",
          "note": "PredTradePanelWidget PascalCase; file kebab-case."
        },
        "7.5": {
          "result": "pass",
          "note": "Out of scope \u2014 English-only UI per product decision 2026-04-21; 7.5 reassigned to UTC datetime rendering",
          "deferReason": "i18n not shipped"
        },
        "7.6": {
          "result": "pass",
          "note": "No dangerous patterns."
        },
        "7.7": {
          "result": "pass",
          "note": "selectedMarket derived inline but not in deps array."
        }
      },
      "notes": "All L7 checks pass."
    },
    "l8": {
      "status": "partial",
      "by": "agent",
      "date": "2026-04-21",
      "checks": {
        "8.1": {
          "result": "pass",
          "note": "No arbitrary font sizes in widget file."
        },
        "8.2": {
          "result": "pass",
          "note": "No arbitrary spacing."
        },
        "8.3": {
          "result": "pass",
          "note": "Delegates to MarketSelector and TradePanelInner (trading components)."
        },
        "8.4": {
          "result": "partial",
          "note": "Agent: no bare img/input/div-onClick in widget file. Human: keyboard through market selector and stake input."
        }
      },
      "notes": "Agent checks pass. Human: 8.4 keyboard + 8.5 resize at minW=4."
    }
  },
  "relationships": {
    "mode": "standalone",
    "masterOf": ["pred-markets-grid"],
    "detailOf": [],
    "selectionKey": "marketId",
    "mergeCandidate": null,
    "keepSeparate": {
      "rationale": "Trade panel is dedicated order entry \u2014 separate from market browser to allow focused trade workflow."
    },
    "notes": "Sets quickTradeMarketId which can be fed by pred-top-markets; also updates selectedMarketId for pred-market-detail cross-widget flow."
  },
  "dataContract": {
    "channels": ["rest"],
    "primary": "rest",
    "cadence": "on-demand",
    "staleness": "near-realtime:<=1s",
    "mockSource": "lib/mocks/fixtures/predictions-data.ts (MOCK_MARKETS) + lib/api/mock-trade-ledger.ts",
    "backendOwner": "unknown",
    "notes": "Production: REST POST to prediction market trade execution service (Polymarket/Kalshi API adapters)."
  },
  "coverage": {
    "assetClasses": ["predictions"],
    "strategies": ["PRED_POLY_ARB_SCE_1M", "PRED_BTC_CEFI_ARB_SCE_5M", "PREDICTION_POLY_ML_DIR_EVT_4H"],
    "venues": ["polymarket", "kalshi"],
    "commonTabs": null,
    "verifiedOn": [],
    "gaps": [
      "Kelly sizing suggestion sourced from TradePanelInner \u2014 not yet wired to real Kelly calculator",
      "Batch mode disable on trade button not yet implemented"
    ],
    "notes": "Widget delegates trade form rendering to TradePanelInner in components/trading/predictions/."
  },
  "knownIssues": [],
  "findings": [
    {
      "level": "l7",
      "check": "7.5",
      "description": "pred-trade-panel-widget.tsx \u2014 1 user-visible string",
      "status": "fixed",
      "fix": "Retired 7.5 i18n check: English-only UI per product decision 2026-04-21"
    }
  ],
  "updatedBy": "agent",
  "updatedAt": "2026-04-21"
}
